xillypy/__init__.py
xillypy/lowlevel.py
xillypy-0.1.1.dist-info/DESCRIPTION.rst
xillypy-0.1.1.dist-info/METADATA
xillypy-0.1.1.dist-info/RECORD
xillypy-0.1.1.dist-info/WHEEL
xillypy-0.1.1.dist-info/metadata.json
xillypy-0.1.1.dist-info/top_level.txt
