Metadata-Version: 2.0
Name: xillypy
Version: 0.1.1
Summary: A simple Xillybus interface written in Python
Home-page: https://github.com/krabo0om/XillyPy
Author: Paul Genssler
Author-email: p.genssler@freenet.de
License: MIT
Keywords: xillybus interface development
Platform: UNKNOWN
Classifier: Development Status :: 4 - Beta
Classifier: Intended Audience :: Developers
Classifier: Topic :: Software Development :: User Interfaces
Classifier: Topic :: System :: Hardware
Classifier: Operating System :: Unix
Classifier: License :: OSI Approved :: MIT License
Classifier: Programming Language :: Python :: 3
Classifier: Programming Language :: Python :: 3.5
Classifier: Programming Language :: Python :: 3.6
